Workbook

Sheet KPI Summary
A1: Project Atlas - KPI Summary
A2: ($ in actuals)
B3: FY2022 | C3: FY2023 | D3: FY2024 | E3: FY2025
A4: Growth
A5: Ending ARR | B5: ='ARR Bridge'!B9 | C5: ='ARR Bridge'!C9 | D5: ='ARR Bridge'!D9 | E5: ='ARR Bridge'!E9
A6: YoY ARR growth % | B6: ='ARR Bridge'!B13 | C6: ='ARR Bridge'!C13 | D6: ='ARR Bridge'!D13 | E6: ='ARR Bridge'!E13
A7: Net $ retention | B7: ='ARR Bridge'!B12 | C7: ='ARR Bridge'!C12 | D7: ='ARR Bridge'!D12 | E7: ='ARR Bridge'!E12
A8: Gross $ retention | B8: ='ARR Bridge'!B11 | C8: ='ARR Bridge'!C11 | D8: ='ARR Bridge'!D11 | E8: ='ARR Bridge'!E11
A9: Customers & Logos
A10: Ending customers | B10: ='Customer & Unit Economics'!B7 | C10: ='Customer & Unit Economics'!C7 | D10: ='Customer & Unit Economics'!D7 | E10: ='Customer & Unit Economics'!E7
A11: New customers | B11: ='Customer & Unit Economics'!B5 | C11: ='Customer & Unit Economics'!C5 | D11: ='Customer & Unit Economics'!D5 | E11: ='Customer & Unit Economics'!E5
A12: Churned customers | B12: ='Customer & Unit Economics'!B6 | C12: ='Customer & Unit Economics'!C6 | D12: ='Customer & Unit Economics'!D6 | E12: ='Customer & Unit Economics'!E6
A13: Logo churn % | B13: ='Customer & Unit Economics'!B8 | C13: ='Customer & Unit Economics'!C8 | D13: ='Customer & Unit Economics'!D8 | E13: ='Customer & Unit Economics'!E8
A14: Average ACV | B14: ='Customer & Unit Economics'!B10 | C14: ='Customer & Unit Economics'!C10 | D14: ='Customer & Unit Economics'!D10 | E14: ='Customer & Unit Economics'!E10
A15: Financials
A16: Total revenue | B16: ='P&L'!B6 | C16: ='P&L'!C6 | D16: ='P&L'!D6 | E16: ='P&L'!E6
A17: Gross margin % | B17: ='P&L'!B9 | C17: ='P&L'!C9 | D17: ='P&L'!D9 | E17: ='P&L'!E9
A18: EBITDA | B18: ='P&L'!B15 | C18: ='P&L'!C15 | D18: ='P&L'!D15 | E18: ='P&L'!E15
A19: EBITDA margin % | B19: ='P&L'!B16 | C19: ='P&L'!C16 | D19: ='P&L'!D16 | E19: ='P&L'!E16
A20: Rule of 40 | B20: ='ARR Bridge'!B13+'P&L'!B16 | C20: ='ARR Bridge'!C13+'P&L'!C16 | D20: ='ARR Bridge'!D13+'P&L'!D16 | E20: ='ARR Bridge'!E13+'P&L'!E16
A21: Unit Economics
A22: CAC (per new logo) | B22: ='Customer & Unit Economics'!B14 | C22: ='Customer & Unit Economics'!C14 | D22: ='Customer & Unit Economics'!D14 | E22: ='Customer & Unit Economics'!E14
A23: CAC payback (months) | B23: ='Customer & Unit Economics'!B15 | C23: ='Customer & Unit Economics'!C15 | D23: ='Customer & Unit Economics'!D15 | E23: ='Customer & Unit Economics'!E15
A24: LTV / CAC | B24: ='Customer & Unit Economics'!B17 | C24: ='Customer & Unit Economics'!C17 | D24: ='Customer & Unit Economics'!D17 | E24: ='Customer & Unit Economics'!E17
A25: Magic number | B25: ='Customer & Unit Economics'!B18 | C25: ='Customer & Unit Economics'!C18 | D25: ='Customer & Unit Economics'!D18 | E25: ='Customer & Unit Economics'!E18

Sheet ARR Bridge
A1: Project Atlas - ARR Bridge
A2: ($ in actuals)
B3: FY2022 | C3: FY2023 | D3: FY2024 | E3: FY2025
A4: Beginning ARR | C4: 216022.8 | D4: 214713.6 | E4: 223283.88
A5: (+) New | C5: 14969.76 | D5: 12625.2 | E5: 23635.68
A6: (+) Expansion | C6: 4359.72 | D6: 4117.68 | E6: 5916.12
A7: (-) Contraction | C7: -4758.72 | D7: -552.6 | E7: -3482.28
A8: (-) Churn | C8: -15879.96 | D8: -7620 | E8: -4536
A9: Ending ARR | B9: 216022.8 | C9: =C4+C5+C6+C7+C8 | D9: =D4+D5+D6+D7+D8 | E9: =E4+E5+E6+E7+E8
A11: Gross $ Retention | C11: =(C4+C7+C8)/C4 | D11: =(D4+D7+D8)/D4 | E11: =(E4+E7+E8)/E4
A12: Net $ Retention | C12: =(C4+C6+C7+C8)/C4 | D12: =(D4+D6+D7+D8)/D4 | E12: =(E4+E6+E7+E8)/E4
A13: YoY ARR Growth | C13: =C9/B9-1 | D13: =D9/C9-1 | E13: =E9/D9-1

Sheet Cohort Retention
A1: Project Atlas - Net Dollar Retention by Cohort
A2: ($ in actuals)
A3: Acquisition Cohort | B3: Logos | C3: Initial ARR | D3: FY2022 | E3: FY2023 | F3: FY2024 | G3: FY2025
A4: FY2022 & Prior | B4: 79 | C4: 216022.8 | D4: 1 | E4: 0.9246424 | F4: 0.9038246 | G4: 0.89182142
A5: FY2023 | B5: 7 | C5: 14969.76 | E5: 1 | F5: 1.0295396 | G5: 1.034734
A6: FY2024 | B6: 5 | C6: 12625.2 | F6: 1 | G6: 1.0327155
A7: FY2025 | B7: 7 | C7: 23635.68 | G7: 1

Sheet P&L
A1: Project Atlas - Income Statement
A2: ($ in actuals)
B3: FY2022 | C3: FY2023 | D3: FY2024 | E3: FY2025
A4: Subscription revenue | B4: 216022.8 | C4: 222721.83 | D4: 218048.68 | E4: 233917.88
A5: Services revenue | B5: 17281.824 | C5: 17817.746 | D5: 17443.894 | E5: 18713.43
A6: Total Revenue | B6: =B4+B5 | C6: =C4+C5 | D6: =D4+D5 | E6: =E4+E5
A7: Cost of revenue | B7: =-B6*0.27 | C7: =-C6*0.25 | D7: =-D6*0.23 | E7: =-E6*0.21
A8: Gross Profit | B8: =B6+B7 | C8: =C6+C7 | D8: =D6+D7 | E8: =E6+E7
A9: Gross Margin % | B9: =B8/B6 | C9: =C8/C6 | D9: =D8/D6 | E9: =E8/E6
A10: Operating expenses
A11: Sales & marketing | B11: =-B6*0.45 | C11: =-C6*0.42 | D11: =-D6*0.39 | E11: =-E6*0.37
A12: Research & development | B12: =-B6*0.22 | C12: =-C6*0.21 | D12: =-D6*0.2 | E12: =-E6*0.19
A13: General & administrative | B13: =-B6*0.15 | C13: =-C6*0.14 | D13: =-D6*0.13 | E13: =-E6*0.12
A14: Total Operating Expenses | B14: =B11+B12+B13 | C14: =C11+C12+C13 | D14: =D11+D12+D13 | E14: =E11+E12+E13
A15: EBITDA | B15: =B8+B14 | C15: =C8+C14 | D15: =D8+D14 | E15: =E8+E14
A16: EBITDA Margin % | B16: =B15/B6 | C16: =C15/C6 | D16: =D15/D6 | E16: =E15/E6
A17: Depreciation & amortization | B17: =-B6*0.03 | C17: =-C6*0.03 | D17: =-D6*0.03 | E17: =-E6*0.03
A18: EBIT | B18: =B15+B17 | C18: =C15+C17 | D18: =D15+D17 | E18: =E15+E17

Sheet Customer & Unit Economics
A1: Project Atlas - Customer & Unit Economics
A2: ($ in actuals)
B3: FY2022 | C3: FY2023 | D3: FY2024 | E3: FY2025
A4: Beginning customers | C4: 79 | D4: 79 | E4: 80
A5: (+) New customers | C5: 6 | D5: 5 | E5: 7
A6: (-) Churned customers | C6: 6 | D6: 4 | E6: 2
A7: Ending customers | B7: 79 | C7: =C4+C5-C6 | D7: =D4+D5-D6 | E7: =E4+E5-E6
A8: Logo churn % | C8: =C6/C4 | D8: =D6/D4 | E8: =E6/E4
A10: Average ACV | B10: ='ARR Bridge'!B9/B7 | C10: ='ARR Bridge'!C9/C7 | D10: ='ARR Bridge'!D9/D7 | E10: ='ARR Bridge'!E9/E7
A11: Gross $ Retention | B11: ='ARR Bridge'!B11 | C11: ='ARR Bridge'!C11 | D11: ='ARR Bridge'!D11 | E11: ='ARR Bridge'!E11
A12: Net $ Retention | B12: ='ARR Bridge'!B12 | C12: ='ARR Bridge'!C12 | D12: ='ARR Bridge'!D12 | E12: ='ARR Bridge'!E12
A14: CAC (per new logo) | C14: =-'P&L'!C11/C5 | D14: =-'P&L'!D11/D5 | E14: =-'P&L'!E11/E5
A15: CAC payback (months) | C15: =C14/(('ARR Bridge'!C5/C5)*'P&L'!C9)*12 | D15: =D14/(('ARR Bridge'!D5/D5)*'P&L'!D9)*12 | E15: =E14/(('ARR Bridge'!E5/E5)*'P&L'!E9)*12
A16: LTV | C16: =C10*'P&L'!C9/C8 | D16: =D10*'P&L'!D9/D8 | E16: =E10*'P&L'!E9/E8
A17: LTV / CAC | C17: =C16/C14 | D17: =D16/D14 | E17: =E16/E14
A18: Magic number | C18: =('ARR Bridge'!C9-'ARR Bridge'!B9)/-'P&L'!B11 | D18: =('ARR Bridge'!D9-'ARR Bridge'!C9)/-'P&L'!C11 | E18: =('ARR Bridge'!E9-'ARR Bridge'!D9)/-'P&L'!D11

Sheet Source Data
B3: Customers | C3: 44926 | D3: 44957 | E3: 44985 | F3: 45016 | G3: 45046 | H3: 45077 | I3: 45107 | J3: 45138 | K3: 45169 | L3: 45199 | M3: 45230 | N3: 45260 | O3: 45291 | P3: 45322 | Q3: 45351 | R3: 45382 | S3: 45412 | T3: 45443 | U3: 45473 | V3: 45504 | W3: 45535 | X3: 45565 | Y3: 45596 | Z3: 45626 | AA3: 45657 | AB3: 45688 | AC3: 45716 | AD3: 45747 | AE3: 45777 | AF3: 45808 | AG3: 45838 | AH3: 45869 | AI3: 45900 | AJ3: 45930 | AK3: 45961 | AL3: 45991 | AM3: 46022
B4: 1 | C4: 179 | D4: 179 | E4: 179 | F4: 179 | G4: 179 | H4: 179 | I4: 179 | J4: 179 | K4: 179 | L4: 179 | M4: 179 | N4: 179 | O4: 179 | P4: 179 | Q4: 179 | R4: 179 | S4: 179 | T4: 179 | U4: 179 | V4: 179 | W4: 179 | X4: 179 | Y4: 179 | Z4: 179 | AA4: 185.27 | AB4: 185.27 | AC4: 185.27 | AD4: 185.27 | AE4: 185.27 | AF4: 185.27 | AG4: 185.27 | AH4: 185.27 | AI4: 185.27 | AJ4: 185.27 | AK4: 185.27 | AL4: 185.27 | AM4: 185.27
B5: 2 | C5: 362.15 | D5: 362.15 | E5: 359 | F5: 359 | G5: 359 | H5: 359 | I5: 359.3 | J5: 359 | K5: 359 | L5: 359 | M5: 359 | N5: 359 | O5: 359 | P5: 359 | Q5: 359 | R5: 359 | S5: 359 | T5: 359 | U5: 359 | V5: 359 | W5: 359 | X5: 359 | Y5: 359 | Z5: 359 | AA5: 359 | AB5: 399 | AC5: 399 | AD5: 399 | AE5: 399 | AF5: 399 | AG5: 399 | AH5: 399 | AI5: 399 | AJ5: 399 | AK5: 399 | AL5: 399 | AM5: 399
B6: 3 | C6: 296.1 | D6: 296.1 | E6: 296.1 | F6: 296.1 | G6: 296.1 | H6: 296.1 | I6: 296.1 | J6: 296.1 | K6: 296.1 | L6: 296.1 | M6: 296.1 | N6: 296.1 | O6: 296.1 | P6: 296.1 | Q6: 296.1 | R6: 296.1 | S6: 296.1 | T6: 296.1 | U6: 296.1 | V6: 296.1 | W6: 296.1 | X6: 296.1 | Y6: 296.1 | Z6: 296.1 | AA6: 296.1 | AB6: 296.1 | AC6: 296.1 | AD6: 296.1 | AE6: 306.46 | AF6: 306.46 | AG6: 306.46 | AH6: 306.46 | AI6: 306.46 | AJ6: 306.46 | AK6: 306.46 | AL6: 306.46 | AM6: 306.46
B7: 4 | C7: 289 | D7: 289 | E7: 289 | F7: 289 | G7: 289 | H7: 289 | I7: 289 | J7: 289 | K7: 289 | L7: 289 | M7: 289 | N7: 289 | O7: 289 | P7: 289 | Q7: 289 | R7: 289 | S7: 289 | T7: 289 | U7: 289 | V7: 289 | W7: 289 | X7: 289 | Y7: 289 | Z7: 289 | AA7: 289 | AB7: 289 | AC7: 289 | AD7: 289 | AE7: 289 | AF7: 289 | AG7: 289 | AH7: 289 | AI7: 289 | AJ7: 289 | AK7: 289 | AL7: 289 | AM7: 289
B8: 5 | C8: 223 | D8: 223 | E8: 223 | F8: 223 | G8: 223 | H8: 223 | I8: 223 | J8: 223 | K8: 234.15 | L8: 234.15 | M8: 210.74 | N8: 210.74 | O8: 210.74 | P8: 210.74 | Q8: 210.74 | R8: 210.74 | S8: 210.74 | T8: 210.74 | U8: 210.74 | V8: 210.74 | W8: 218.12 | X8: 218.12 | Y8: 218.12 | Z8: 218.12 | AA8: 218.12 | AB8: 218.12 | AC8: 218.12 | AD8: 218.12 | AE8: 218.12 | AF8: 218.12 | AG8: 218.12 | AH8: 218.12 | AI8: 218.12 | AJ8: 225.75 | AK8: 225.75 | AL8: 225.75 | AM8: 225.75
B9: 6 | C9: 279 | D9: 279 | E9: 279 | F9: 279 | G9: 279 | H9: 378 | I9: 279 | J9: 279 | K9: 279 | L9: 279 | M9: 279 | N9: 279 | O9: 279 | P9: 279 | Q9: 279 | R9: 279 | S9: 279 | T9: 279 | U9: 279 | V9: 279 | W9: 279 | X9: 279 | Y9: 279 | Z9: 279 | AA9: 279 | AB9: 279 | AC9: 279 | AD9: 279 | AE9: 279 | AF9: 288.77 | AG9: 288.77 | AH9: 288.77 | AI9: 288.77 | AJ9: 288.77 | AK9: 288.77 | AL9: 288.77 | AM9: 288.77
B10: 7 | C10: 170.05 | D10: 170.05 | E10: 170.05 | F10: 170.05 | G10: 170.05 | H10: 170.05 | I10: 170.05 | J10: 170.05 | K10: 170.05 | L10: 170.05 | M10: 179 | N10: 179 | O10: 179 | P10: 179 | Q10: 179 | R10: 179 | S10: 179 | T10: 179 | U10: 179 | V10: 179 | W10: 179 | X10: 179 | Y10: 179 | Z10: 179 | AA10: 179 | AB10: 179 | AC10: 179 | AD10: 179 | AE10: 179 | AF10: 185.27 | AG10: 185.27 | AH10: 185.27 | AI10: 185.27 | AJ10: 185.27 | AK10: 185.27 | AL10: 185.27 | AM10: 185.27
B11: 8 | C11: 99 | D11: 99 | E11: 99 | F11: 99 | G11: 99 | H11: 99 | I11: 99 | J11: 99 | K11: 99 | L11: 99 | M11: 99 | N11: 99 | O11: 99 | P11: 28.71 | Q11: 0 | R11: 0 | S11: 0 | T11: 0 | U11: 0 | V11: 0 | W11: 0 | X11: 0 | Y11: 0 | Z11: 0 | AA11: 0 | AB11: 0 | AC11: 0 | AD11: 0 | AE11: 0 | AF11: 0 | AG11: 0 | AH11: 0 | AI11: 0 | AJ11: 0 | AK11: 0 | AL11: 0 | AM11: 0
B12: 9 | C12: 229 | D12: 229 | E12: 229 | F12: 229 | G12: 229 | H12: 229 | I12: 229 | J12: 229 | K12: 229 | L12: 229 | M12: 229 | N12: 229 | O12: 229 | P12: 229 | Q12: 229 | R12: 229 | S12: 229 | T12: 229 | U12: 229 | V12: 229 | W12: 229 | X12: 229 | Y12: 229 | Z12: 229 | AA12: 229 | AB12: 229 | AC12: 229 | AD12: 229 | AE12: 229 | AF12: 229 | AG12: 229 | AH12: 229 | AI12: 237.02 | AJ12: 237.02 | AK12: 237.02 | AL12: 237.02 | AM12: 237.02
B13: 10 | C13: 279 | D13: 279 | E13: 279 | F13: 279 | G13: 279 | H13: 279 | I13: 179 | J13: 179 | K13: 179 | L13: 179 | M13: 179 | N13: 179 | O13: 179 | P13: 179 | Q13: 179 | R13: 179 | S13: 179 | T13: 179 | U13: 179 | V13: 179 | W13: 179 | X13: 179 | Y13: 179 | Z13: 179 | AA13: 179 | AB13: 179 | AC13: 179 | AD13: 179 | AE13: 179 | AF13: 179 | AG13: 179 | AH13: 179 | AI13: 179 | AJ13: 185.27 | AK13: 185.27 | AL13: 185.27 | AM13: 185.27
B14: 11 | C14: 170.05 | D14: 170.05 | E14: 170.05 | F14: 170.05 | G14: 170.05 | H14: 170.05 | I14: 170.05 | J14: 170.05 | K14: 170.05 | L14: 170.05 | M14: 179 | N14: 179 | O14: 179 | P14: 179 | Q14: 179 | R14: 179 | S14: 179 | T14: 179 | U14: 179 | V14: 179 | W14: 179 | X14: 179 | Y14: 179 | Z14: 179 | AA14: 179 | AB14: 179 | AC14: 179 | AD14: 179 | AE14: 179 | AF14: 179 | AG14: 179 | AH14: 179 | AI14: 179 | AJ14: 179 | AK14: 179 | AL14: 179 | AM14: 179
B15: 12 | C15: 284.05 | D15: 284.05 | E15: 284.05 | F15: 284.05 | G15: 284.05 | H15: 284.05 | I15: 290.03 | J15: 290.03 | K15: 290.03 | L15: 290.03 | M15: 281.33 | N15: 281.33 | O15: 281.33 | P15: 281.33 | Q15: 281.33 | R15: 281.33 | S15: 281.33 | T15: 290.03 | U15: 290.03 | V15: 290.03 | W15: 290.03 | X15: 290.03 | Y15: 290.03 | Z15: 300.19 | AA15: 300.19 | AB15: 300.19 | AC15: 300.19 | AD15: 300.19 | AE15: 294 | AF15: 294 | AG15: 294 | AH15: 294 | AI15: 294 | AJ15: 294 | AK15: 294 | AL15: 294 | AM15: 294
... B103: 100 | C103: 259 | D103: 259 | E103: 259 | F103: 259 | G103: 259 | H103: 259 | I103: 259 | J103: 259 | K103: 259 | L103: 259 | M103: 259 | N103: 259 | O103: 259 | P103: 259 | Q103: 259 | R103: 259 | S103: 259 | T103: 259 | U103: 259 | V103: 259 | W103: 259 | X103: 279 | Y103: 279 | Z103: 279 | AA103: 279 | AB103: 0 | AC103: 0 | AD103: 0 | AE103: 0 | AF103: 0 | AG103: 0 | AH103: 0 | AI103: 0 | AJ103: 0 | AK103: 0 | AL103: 0 | AM103: 0
